{
  "candles": [
    {
      "timestamp": 1778614832868,
      "open": 1.3523,
      "high": 1.3523,
      "low": 1.3523,
      "close": 1.3523
    },
    {
      "timestamp": 1778615178031,
      "open": 1.3523,
      "high": 1.3523,
      "low": 1.3523,
      "close": 1.3523
    },
    {
      "timestamp": 1778615436139,
      "open": 1.3523,
      "high": 1.3523,
      "low": 1.3523,
      "close": 1.3523
    },
    {
      "timestamp": 1778615782167,
      "open": 1.3523,
      "high": 1.3523,
      "low": 1.3523,
      "close": 1.3523
    },
    {
      "timestamp": 1778616051432,
      "open": 1.3523,
      "high": 1.3523,
      "low": 1.3523,
      "close": 1.3523
    },
    {
      "timestamp": 1778616380805,
      "open": 1.3523,
      "high": 1.3523,
      "low": 1.3523,
      "close": 1.3523
    },
    {
      "timestamp": 1778616630010,
      "open": 1.3523,
      "high": 1.3523,
      "low": 1.3523,
      "close": 1.3523
    },
    {
      "timestamp": 1778616982451,
      "open": 1.3523,
      "high": 1.3523,
      "low": 1.3523,
      "close": 1.3523
    },
    {
      "timestamp": 1778617235723,
      "open": 1.3523,
      "high": 1.3523,
      "low": 1.3523,
      "close": 1.3523
    },
    {
      "timestamp": 1778617578017,
      "open": 1.3523,
      "high": 1.3523,
      "low": 1.3523,
      "close": 1.3523
    },
    {
      "timestamp": 1778617839189,
      "open": 1.3523,
      "high": 1.3523,
      "low": 1.3523,
      "close": 1.3523
    },
    {
      "timestamp": 1778618180193,
      "open": 1.3523,
      "high": 1.3523,
      "low": 1.3523,
      "close": 1.3523
    },
    {
      "timestamp": 1778618430557,
      "open": 1.3523,
      "high": 1.3523,
      "low": 1.3523,
      "close": 1.3523
    },
    {
      "timestamp": 1778618778805,
      "open": 1.3523,
      "high": 1.3523,
      "low": 1.3523,
      "close": 1.3523
    },
    {
      "timestamp": 1778619026032,
      "open": 1.3523,
      "high": 1.3523,
      "low": 1.3523,
      "close": 1.3523
    },
    {
      "timestamp": 1778619381624,
      "open": 1.3523,
      "high": 1.3523,
      "low": 1.3523,
      "close": 1.3523
    },
    {
      "timestamp": 1778619657609,
      "open": 1.3523,
      "high": 1.3523,
      "low": 1.3523,
      "close": 1.3523
    },
    {
      "timestamp": 1778619983747,
      "open": 1.3523,
      "high": 1.3523,
      "low": 1.3523,
      "close": 1.3523
    },
    {
      "timestamp": 1778620232900,
      "open": 1.3523,
      "high": 1.3523,
      "low": 1.3523,
      "close": 1.3523
    },
    {
      "timestamp": 1778620581564,
      "open": 1.3523,
      "high": 1.3523,
      "low": 1.3523,
      "close": 1.3523
    },
    {
      "timestamp": 1778620835102,
      "open": 1.3523,
      "high": 1.3523,
      "low": 1.3523,
      "close": 1.3523
    },
    {
      "timestamp": 1778621176734,
      "open": 1.3523,
      "high": 1.3523,
      "low": 1.3523,
      "close": 1.3523
    },
    {
      "timestamp": 1778621441187,
      "open": 1.3523,
      "high": 1.3523,
      "low": 1.3523,
      "close": 1.3523
    },
    {
      "timestamp": 1778621781746,
      "open": 1.3523,
      "high": 1.3523,
      "low": 1.3523,
      "close": 1.3523
    },
    {
      "timestamp": 1778622026280,
      "open": 1.3523,
      "high": 1.3523,
      "low": 1.3523,
      "close": 1.3523
    },
    {
      "timestamp": 1778622380258,
      "open": 1.3523,
      "high": 1.3523,
      "low": 1.3523,
      "close": 1.3523
    },
    {
      "timestamp": 1778622626144,
      "open": 1.3523,
      "high": 1.3523,
      "low": 1.3523,
      "close": 1.3523
    },
    {
      "timestamp": 1778622977034,
      "open": 1.3523,
      "high": 1.3523,
      "low": 1.3523,
      "close": 1.3523
    },
    {
      "timestamp": 1778623251508,
      "open": 1.3523,
      "high": 1.3523,
      "low": 1.3523,
      "close": 1.3523
    },
    {
      "timestamp": 1778623578446,
      "open": 1.3523,
      "high": 1.3523,
      "low": 1.3523,
      "close": 1.3523
    },
    {
      "timestamp": 1778623826228,
      "open": 1.3523,
      "high": 1.3523,
      "low": 1.3523,
      "close": 1.3523
    },
    {
      "timestamp": 1778624184625,
      "open": 1.3523,
      "high": 1.3523,
      "low": 1.3523,
      "close": 1.3523
    },
    {
      "timestamp": 1778624437806,
      "open": 1.3523,
      "high": 1.3523,
      "low": 1.3523,
      "close": 1.3523
    },
    {
      "timestamp": 1778624779783,
      "open": 1.3523,
      "high": 1.3523,
      "low": 1.3523,
      "close": 1.3523
    },
    {
      "timestamp": 1778625044742,
      "open": 1.3523,
      "high": 1.3523,
      "low": 1.3523,
      "close": 1.3523
    },
    {
      "timestamp": 1778625384960,
      "open": 1.3523,
      "high": 1.3523,
      "low": 1.3523,
      "close": 1.3523
    },
    {
      "timestamp": 1778625625119,
      "open": 1.3523,
      "high": 1.3523,
      "low": 1.3523,
      "close": 1.3523
    },
    {
      "timestamp": 1778625985316,
      "open": 1.3523,
      "high": 1.3523,
      "low": 1.3523,
      "close": 1.3523
    },
    {
      "timestamp": 1778626232763,
      "open": 1.3523,
      "high": 1.3523,
      "low": 1.3523,
      "close": 1.3523
    },
    {
      "timestamp": 1778626577637,
      "open": 1.3523,
      "high": 1.3523,
      "low": 1.3523,
      "close": 1.3523
    },
    {
      "timestamp": 1778626848031,
      "open": 1.3523,
      "high": 1.3523,
      "low": 1.3523,
      "close": 1.3523
    },
    {
      "timestamp": 1778627177743,
      "open": 1.3523,
      "high": 1.3523,
      "low": 1.3523,
      "close": 1.3523
    },
    {
      "timestamp": 1778627429487,
      "open": 1.3523,
      "high": 1.3523,
      "low": 1.3523,
      "close": 1.3523
    },
    {
      "timestamp": 1778627779948,
      "open": 1.3523,
      "high": 1.3523,
      "low": 1.3523,
      "close": 1.3523
    },
    {
      "timestamp": 1778628028044,
      "open": 1.3523,
      "high": 1.3523,
      "low": 1.3523,
      "close": 1.3523
    },
    {
      "timestamp": 1778628383000,
      "open": 1.3523,
      "high": 1.3523,
      "low": 1.3523,
      "close": 1.3523
    },
    {
      "timestamp": 1778628637422,
      "open": 1.3523,
      "high": 1.3523,
      "low": 1.3523,
      "close": 1.3523
    },
    {
      "timestamp": 1778628977081,
      "open": 1.3523,
      "high": 1.3523,
      "low": 1.3523,
      "close": 1.3523
    },
    {
      "timestamp": 1778629231937,
      "open": 1.3523,
      "high": 1.3523,
      "low": 1.3523,
      "close": 1.3523
    },
    {
      "timestamp": 1778629586294,
      "open": 1.3523,
      "high": 1.3523,
      "low": 1.3523,
      "close": 1.3523
    },
    {
      "timestamp": 1778629824603,
      "open": 1.3523,
      "high": 1.3523,
      "low": 1.3523,
      "close": 1.3523
    },
    {
      "timestamp": 1778630176969,
      "open": 1.3523,
      "high": 1.3523,
      "low": 1.3523,
      "close": 1.3523
    },
    {
      "timestamp": 1778630460600,
      "open": 1.3523,
      "high": 1.3523,
      "low": 1.3523,
      "close": 1.3523
    },
    {
      "timestamp": 1778630777664,
      "open": 1.3523,
      "high": 1.3523,
      "low": 1.3523,
      "close": 1.3523
    },
    {
      "timestamp": 1778631027232,
      "open": 1.3523,
      "high": 1.3523,
      "low": 1.3523,
      "close": 1.3523
    },
    {
      "timestamp": 1778631382617,
      "open": 1.3523,
      "high": 1.3523,
      "low": 1.3523,
      "close": 1.3523
    },
    {
      "timestamp": 1778631629880,
      "open": 1.3523,
      "high": 1.3523,
      "low": 1.3523,
      "close": 1.3523
    },
    {
      "timestamp": 1778631979530,
      "open": 1.3523,
      "high": 1.3523,
      "low": 1.3523,
      "close": 1.3523
    },
    {
      "timestamp": 1778632241113,
      "open": 1.3523,
      "high": 1.3523,
      "low": 1.3523,
      "close": 1.3523
    },
    {
      "timestamp": 1778632576125,
      "open": 1.3523,
      "high": 1.3523,
      "low": 1.3523,
      "close": 1.3523
    },
    {
      "timestamp": 1778632832547,
      "open": 1.3523,
      "high": 1.3523,
      "low": 1.3523,
      "close": 1.3523
    },
    {
      "timestamp": 1778633181656,
      "open": 1.3523,
      "high": 1.3523,
      "low": 1.3523,
      "close": 1.3523
    },
    {
      "timestamp": 1778633425445,
      "open": 1.3523,
      "high": 1.3523,
      "low": 1.3523,
      "close": 1.3523
    },
    {
      "timestamp": 1778633780957,
      "open": 1.3523,
      "high": 1.3523,
      "low": 1.3523,
      "close": 1.3523
    },
    {
      "timestamp": 1778634049611,
      "open": 1.3523,
      "high": 1.3523,
      "low": 1.3523,
      "close": 1.3523
    },
    {
      "timestamp": 1778634376680,
      "open": 1.3523,
      "high": 1.3523,
      "low": 1.3523,
      "close": 1.3523
    },
    {
      "timestamp": 1778634629671,
      "open": 1.3523,
      "high": 1.3523,
      "low": 1.3523,
      "close": 1.3523
    },
    {
      "timestamp": 1778634982813,
      "open": 1.3523,
      "high": 1.3523,
      "low": 1.3523,
      "close": 1.3523
    },
    {
      "timestamp": 1778635226477,
      "open": 1.3523,
      "high": 1.3523,
      "low": 1.3523,
      "close": 1.3523
    },
    {
      "timestamp": 1778635580751,
      "open": 1.3523,
      "high": 1.3523,
      "low": 1.3523,
      "close": 1.3523
    },
    {
      "timestamp": 1778635848036,
      "open": 1.3523,
      "high": 1.3523,
      "low": 1.3523,
      "close": 1.3523
    },
    {
      "timestamp": 1778636177316,
      "open": 1.3523,
      "high": 1.3523,
      "low": 1.3523,
      "close": 1.3523
    },
    {
      "timestamp": 1778636428029,
      "open": 1.3523,
      "high": 1.3523,
      "low": 1.3523,
      "close": 1.3523
    },
    {
      "timestamp": 1778636775997,
      "open": 1.3523,
      "high": 1.3523,
      "low": 1.3523,
      "close": 1.3523
    },
    {
      "timestamp": 1778637035448,
      "open": 1.3523,
      "high": 1.3523,
      "low": 1.3523,
      "close": 1.3523
    },
    {
      "timestamp": 1778637377101,
      "open": 1.3523,
      "high": 1.3523,
      "low": 1.3523,
      "close": 1.3523
    },
    {
      "timestamp": 1778637655619,
      "open": 1.3523,
      "high": 1.3523,
      "low": 1.3523,
      "close": 1.3523
    },
    {
      "timestamp": 1778637982063,
      "open": 1.3523,
      "high": 1.3523,
      "low": 1.3523,
      "close": 1.3523
    },
    {
      "timestamp": 1778638224643,
      "open": 1.3523,
      "high": 1.3523,
      "low": 1.3523,
      "close": 1.3523
    },
    {
      "timestamp": 1778638576760,
      "open": 1.3523,
      "high": 1.3523,
      "low": 1.3523,
      "close": 1.3523
    },
    {
      "timestamp": 1778638826503,
      "open": 1.3523,
      "high": 1.3523,
      "low": 1.3523,
      "close": 1.3523
    },
    {
      "timestamp": 1778639184192,
      "open": 1.3523,
      "high": 1.3523,
      "low": 1.3523,
      "close": 1.3523
    },
    {
      "timestamp": 1778639441288,
      "open": 1.3523,
      "high": 1.3523,
      "low": 1.3523,
      "close": 1.3523
    },
    {
      "timestamp": 1778639776049,
      "open": 1.3523,
      "high": 1.3523,
      "low": 1.3523,
      "close": 1.3523
    },
    {
      "timestamp": 1778640025655,
      "open": 1.3523,
      "high": 1.3523,
      "low": 1.3523,
      "close": 1.3523
    },
    {
      "timestamp": 1778640378860,
      "open": 1.3523,
      "high": 1.3523,
      "low": 1.3523,
      "close": 1.3523
    },
    {
      "timestamp": 1778640631804,
      "open": 1.3523,
      "high": 1.3523,
      "low": 1.3523,
      "close": 1.3523
    },
    {
      "timestamp": 1778640976135,
      "open": 1.3523,
      "high": 1.3523,
      "low": 1.3523,
      "close": 1.3523
    },
    {
      "timestamp": 1778641256588,
      "open": 1.3523,
      "high": 1.3523,
      "low": 1.3523,
      "close": 1.3523
    },
    {
      "timestamp": 1778641577102,
      "open": 1.3523,
      "high": 1.3523,
      "low": 1.3523,
      "close": 1.3523
    },
    {
      "timestamp": 1778641828167,
      "open": 1.3523,
      "high": 1.3523,
      "low": 1.3523,
      "close": 1.3523
    },
    {
      "timestamp": 1778642180193,
      "open": 1.3523,
      "high": 1.3523,
      "low": 1.3523,
      "close": 1.3523
    },
    {
      "timestamp": 1778642428932,
      "open": 1.3523,
      "high": 1.3523,
      "low": 1.3523,
      "close": 1.3523
    },
    {
      "timestamp": 1778642778811,
      "open": 1.3523,
      "high": 1.3523,
      "low": 1.3523,
      "close": 1.3523
    },
    {
      "timestamp": 1778643037907,
      "open": 1.3523,
      "high": 1.3523,
      "low": 1.3523,
      "close": 1.3523
    },
    {
      "timestamp": 1778643376450,
      "open": 1.3523,
      "high": 1.3523,
      "low": 1.3523,
      "close": 1.3523
    },
    {
      "timestamp": 1778643627200,
      "open": 1.3523,
      "high": 1.3523,
      "low": 1.3523,
      "close": 1.3523
    },
    {
      "timestamp": 1778643976247,
      "open": 1.3523,
      "high": 1.3523,
      "low": 1.3523,
      "close": 1.3523
    },
    {
      "timestamp": 1778644230685,
      "open": 1.3523,
      "high": 1.3523,
      "low": 1.3523,
      "close": 1.3523
    },
    {
      "timestamp": 1778644576567,
      "open": 1.3523,
      "high": 1.3523,
      "low": 1.3523,
      "close": 1.3523
    },
    {
      "timestamp": 1778644855307,
      "open": 1.3523,
      "high": 1.3523,
      "low": 1.3523,
      "close": 1.3523
    },
    {
      "timestamp": 1778645177063,
      "open": 1.3523,
      "high": 1.3523,
      "low": 1.3523,
      "close": 1.3523
    },
    {
      "timestamp": 1778645436116,
      "open": 1.3523,
      "high": 1.3523,
      "low": 1.3523,
      "close": 1.3523
    },
    {
      "timestamp": 1778645776643,
      "open": 1.3523,
      "high": 1.3523,
      "low": 1.3523,
      "close": 1.3523
    },
    {
      "timestamp": 1778646025185,
      "open": 1.3523,
      "high": 1.3523,
      "low": 1.3523,
      "close": 1.3523
    },
    {
      "timestamp": 1778646375598,
      "open": 1.3523,
      "high": 1.3523,
      "low": 1.3523,
      "close": 1.3523
    },
    {
      "timestamp": 1778646636819,
      "open": 1.3523,
      "high": 1.3523,
      "low": 1.3523,
      "close": 1.3523
    },
    {
      "timestamp": 1778646982588,
      "open": 1.3523,
      "high": 1.3523,
      "low": 1.3523,
      "close": 1.3523
    },
    {
      "timestamp": 1778647226066,
      "open": 1.3523,
      "high": 1.3523,
      "low": 1.3523,
      "close": 1.3523
    },
    {
      "timestamp": 1778647589133,
      "open": 1.3523,
      "high": 1.3523,
      "low": 1.3523,
      "close": 1.3523
    },
    {
      "timestamp": 1778647831895,
      "open": 1.3523,
      "high": 1.3523,
      "low": 1.3523,
      "close": 1.3523
    },
    {
      "timestamp": 1778648185065,
      "open": 1.3523,
      "high": 1.3523,
      "low": 1.3523,
      "close": 1.3523
    },
    {
      "timestamp": 1778648447479,
      "open": 1.3523,
      "high": 1.3523,
      "low": 1.3523,
      "close": 1.3523
    },
    {
      "timestamp": 1778648777140,
      "open": 1.3523,
      "high": 1.3523,
      "low": 1.3523,
      "close": 1.3523
    },
    {
      "timestamp": 1778649025485,
      "open": 1.3523,
      "high": 1.3523,
      "low": 1.3523,
      "close": 1.3523
    },
    {
      "timestamp": 1778649379424,
      "open": 1.3523,
      "high": 1.3523,
      "low": 1.3523,
      "close": 1.3523
    },
    {
      "timestamp": 1778649627622,
      "open": 1.3523,
      "high": 1.3523,
      "low": 1.3523,
      "close": 1.3523
    },
    {
      "timestamp": 1778649985644,
      "open": 1.3523,
      "high": 1.3523,
      "low": 1.3523,
      "close": 1.3523
    },
    {
      "timestamp": 1778650243895,
      "open": 1.3523,
      "high": 1.3523,
      "low": 1.3523,
      "close": 1.3523
    },
    {
      "timestamp": 1778650578014,
      "open": 1.3523,
      "high": 1.3523,
      "low": 1.3523,
      "close": 1.3523
    },
    {
      "timestamp": 1778650833686,
      "open": 1.3523,
      "high": 1.3523,
      "low": 1.3523,
      "close": 1.3523
    },
    {
      "timestamp": 1778651176110,
      "open": 1.3523,
      "high": 1.3523,
      "low": 1.3523,
      "close": 1.3523
    },
    {
      "timestamp": 1778651427379,
      "open": 1.3523,
      "high": 1.3523,
      "low": 1.3523,
      "close": 1.3523
    },
    {
      "timestamp": 1778651786194,
      "open": 1.3523,
      "high": 1.3523,
      "low": 1.3523,
      "close": 1.3523
    },
    {
      "timestamp": 1778652055784,
      "open": 1.3523,
      "high": 1.3523,
      "low": 1.3523,
      "close": 1.3523
    },
    {
      "timestamp": 1778652386541,
      "open": 1.3523,
      "high": 1.3523,
      "low": 1.3523,
      "close": 1.3523
    },
    {
      "timestamp": 1778652625801,
      "open": 1.3523,
      "high": 1.3523,
      "low": 1.3523,
      "close": 1.3523
    },
    {
      "timestamp": 1778652983687,
      "open": 1.3523,
      "high": 1.3523,
      "low": 1.3523,
      "close": 1.3523
    },
    {
      "timestamp": 1778653232234,
      "open": 1.3523,
      "high": 1.3523,
      "low": 1.3523,
      "close": 1.3523
    },
    {
      "timestamp": 1778653585648,
      "open": 1.3523,
      "high": 1.3523,
      "low": 1.3523,
      "close": 1.3523
    },
    {
      "timestamp": 1778653838402,
      "open": 1.3523,
      "high": 1.3523,
      "low": 1.3523,
      "close": 1.3523
    },
    {
      "timestamp": 1778654183059,
      "open": 1.3523,
      "high": 1.3523,
      "low": 1.3523,
      "close": 1.3523
    },
    {
      "timestamp": 1778654432043,
      "open": 1.3523,
      "high": 1.3523,
      "low": 1.3523,
      "close": 1.3523
    },
    {
      "timestamp": 1778654776372,
      "open": 1.3523,
      "high": 1.3523,
      "low": 1.3523,
      "close": 1.3523
    },
    {
      "timestamp": 1778655032326,
      "open": 1.3523,
      "high": 1.3523,
      "low": 1.3523,
      "close": 1.3523
    },
    {
      "timestamp": 1778655382989,
      "open": 1.3523,
      "high": 1.3523,
      "low": 1.3523,
      "close": 1.3523
    },
    {
      "timestamp": 1778655657335,
      "open": 1.3523,
      "high": 1.3523,
      "low": 1.3523,
      "close": 1.3523
    },
    {
      "timestamp": 1778655987237,
      "open": 1.3523,
      "high": 1.3523,
      "low": 1.3523,
      "close": 1.3523
    },
    {
      "timestamp": 1778656236295,
      "open": 1.3523,
      "high": 1.3523,
      "low": 1.3523,
      "close": 1.3523
    },
    {
      "timestamp": 1778656584566,
      "open": 1.3523,
      "high": 1.3523,
      "low": 1.3523,
      "close": 1.3523
    },
    {
      "timestamp": 1778656828564,
      "open": 1.3523,
      "high": 1.3523,
      "low": 1.3523,
      "close": 1.3523
    },
    {
      "timestamp": 1778657180082,
      "open": 1.3523,
      "high": 1.3523,
      "low": 1.3523,
      "close": 1.3523
    },
    {
      "timestamp": 1778657441062,
      "open": 1.3523,
      "high": 1.3523,
      "low": 1.3523,
      "close": 1.3523
    },
    {
      "timestamp": 1778657779515,
      "open": 1.3523,
      "high": 1.3523,
      "low": 1.3523,
      "close": 1.3523
    },
    {
      "timestamp": 1778658027979,
      "open": 1.3523,
      "high": 1.3523,
      "low": 1.3523,
      "close": 1.3523
    },
    {
      "timestamp": 1778658385135,
      "open": 1.3523,
      "high": 1.3523,
      "low": 1.3523,
      "close": 1.3523
    },
    {
      "timestamp": 1778658629698,
      "open": 1.3523,
      "high": 1.3523,
      "low": 1.3523,
      "close": 1.3523
    },
    {
      "timestamp": 1778658987691,
      "open": 1.3523,
      "high": 1.3523,
      "low": 1.3523,
      "close": 1.3523
    },
    {
      "timestamp": 1778659259144,
      "open": 1.3523,
      "high": 1.3523,
      "low": 1.3523,
      "close": 1.3523
    },
    {
      "timestamp": 1778659580885,
      "open": 1.3523,
      "high": 1.3523,
      "low": 1.3523,
      "close": 1.3523
    },
    {
      "timestamp": 1778659836886,
      "open": 1.3523,
      "high": 1.3523,
      "low": 1.3523,
      "close": 1.3523
    },
    {
      "timestamp": 1778660180759,
      "open": 1.3523,
      "high": 1.3523,
      "low": 1.3523,
      "close": 1.3523
    },
    {
      "timestamp": 1778660429698,
      "open": 1.3523,
      "high": 1.3523,
      "low": 1.3523,
      "close": 1.3523
    },
    {
      "timestamp": 1778660785013,
      "open": 1.3523,
      "high": 1.3523,
      "low": 1.3523,
      "close": 1.3523
    },
    {
      "timestamp": 1778661046988,
      "open": 1.3523,
      "high": 1.3523,
      "low": 1.3523,
      "close": 1.3523
    },
    {
      "timestamp": 1778661379385,
      "open": 1.3523,
      "high": 1.3523,
      "low": 1.3523,
      "close": 1.3523
    },
    {
      "timestamp": 1778661633256,
      "open": 1.3523,
      "high": 1.3523,
      "low": 1.3523,
      "close": 1.3523
    },
    {
      "timestamp": 1778661985176,
      "open": 1.3523,
      "high": 1.3523,
      "low": 1.3523,
      "close": 1.3523
    },
    {
      "timestamp": 1778662234677,
      "open": 1.3523,
      "high": 1.3523,
      "low": 1.3523,
      "close": 1.3523
    },
    {
      "timestamp": 1778662584183,
      "open": 1.3523,
      "high": 1.3523,
      "low": 1.3523,
      "close": 1.3523
    },
    {
      "timestamp": 1778662853324,
      "open": 1.3523,
      "high": 1.3523,
      "low": 1.3523,
      "close": 1.3523
    },
    {
      "timestamp": 1778663185663,
      "open": 1.3523,
      "high": 1.3523,
      "low": 1.3523,
      "close": 1.3523
    },
    {
      "timestamp": 1778663440486,
      "open": 1.3523,
      "high": 1.3523,
      "low": 1.3523,
      "close": 1.3523
    },
    {
      "timestamp": 1778663785250,
      "open": 1.3523,
      "high": 1.3523,
      "low": 1.3523,
      "close": 1.3523
    },
    {
      "timestamp": 1778664035210,
      "open": 1.3523,
      "high": 1.3523,
      "low": 1.3523,
      "close": 1.3523
    },
    {
      "timestamp": 1778664380925,
      "open": 1.3523,
      "high": 1.3523,
      "low": 1.3523,
      "close": 1.3523
    },
    {
      "timestamp": 1778664639422,
      "open": 1.3523,
      "high": 1.3523,
      "low": 1.3523,
      "close": 1.3523
    },
    {
      "timestamp": 1778664984910,
      "open": 1.3523,
      "high": 1.3523,
      "low": 1.3523,
      "close": 1.3523
    },
    {
      "timestamp": 1778665232589,
      "open": 1.3523,
      "high": 1.3523,
      "low": 1.3523,
      "close": 1.3523
    },
    {
      "timestamp": 1778665584295,
      "open": 1.3523,
      "high": 1.3523,
      "low": 1.3523,
      "close": 1.3523
    },
    {
      "timestamp": 1778665835280,
      "open": 1.3523,
      "high": 1.3523,
      "low": 1.3523,
      "close": 1.3523
    },
    {
      "timestamp": 1778666178435,
      "open": 1.3523,
      "high": 1.3523,
      "low": 1.3523,
      "close": 1.3523
    },
    {
      "timestamp": 1778666458231,
      "open": 1.3523,
      "high": 1.3523,
      "low": 1.3523,
      "close": 1.3523
    },
    {
      "timestamp": 1778666786438,
      "open": 1.3523,
      "high": 1.3523,
      "low": 1.3523,
      "close": 1.3523
    },
    {
      "timestamp": 1778667034836,
      "open": 1.3523,
      "high": 1.3523,
      "low": 1.3523,
      "close": 1.3523
    },
    {
      "timestamp": 1778667387122,
      "open": 1.3523,
      "high": 1.3523,
      "low": 1.3523,
      "close": 1.3523
    },
    {
      "timestamp": 1778667628717,
      "open": 1.3523,
      "high": 1.3523,
      "low": 1.3523,
      "close": 1.3523
    },
    {
      "timestamp": 1778667980197,
      "open": 1.3523,
      "high": 1.3523,
      "low": 1.3523,
      "close": 1.3523
    },
    {
      "timestamp": 1778668249477,
      "open": 1.3523,
      "high": 1.3523,
      "low": 1.3523,
      "close": 1.3523
    },
    {
      "timestamp": 1778668583240,
      "open": 1.3523,
      "high": 1.3523,
      "low": 1.3523,
      "close": 1.3523
    },
    {
      "timestamp": 1778668827166,
      "open": 1.3523,
      "high": 1.3523,
      "low": 1.3523,
      "close": 1.3523
    },
    {
      "timestamp": 1778669188031,
      "open": 1.3523,
      "high": 1.3523,
      "low": 1.3523,
      "close": 1.3523
    },
    {
      "timestamp": 1778669426609,
      "open": 1.3523,
      "high": 1.3523,
      "low": 1.3523,
      "close": 1.3523
    },
    {
      "timestamp": 1778669778993,
      "open": 1.3523,
      "high": 1.3523,
      "low": 1.3523,
      "close": 1.3523
    },
    {
      "timestamp": 1778670061388,
      "open": 1.3523,
      "high": 1.3523,
      "low": 1.3523,
      "close": 1.3523
    },
    {
      "timestamp": 1778670383162,
      "open": 1.3523,
      "high": 1.3523,
      "low": 1.3523,
      "close": 1.3523
    },
    {
      "timestamp": 1778670629325,
      "open": 1.3523,
      "high": 1.3523,
      "low": 1.3523,
      "close": 1.3523
    },
    {
      "timestamp": 1778670984470,
      "open": 1.3523,
      "high": 1.3523,
      "low": 1.3523,
      "close": 1.3523
    },
    {
      "timestamp": 1778671236907,
      "open": 1.3523,
      "high": 1.3523,
      "low": 1.3523,
      "close": 1.3523
    },
    {
      "timestamp": 1778671581095,
      "open": 1.3523,
      "high": 1.3523,
      "low": 1.3523,
      "close": 1.3523
    },
    {
      "timestamp": 1778671843659,
      "open": 1.3523,
      "high": 1.3523,
      "low": 1.3523,
      "close": 1.3523
    },
    {
      "timestamp": 1778672182883,
      "open": 1.3523,
      "high": 1.3523,
      "low": 1.3523,
      "close": 1.3523
    },
    {
      "timestamp": 1778672433553,
      "open": 1.3523,
      "high": 1.3523,
      "low": 1.3523,
      "close": 1.3523
    },
    {
      "timestamp": 1778672778493,
      "open": 1.3523,
      "high": 1.3523,
      "low": 1.3523,
      "close": 1.3523
    },
    {
      "timestamp": 1778673027003,
      "open": 1.3523,
      "high": 1.3523,
      "low": 1.3523,
      "close": 1.3523
    },
    {
      "timestamp": 1778673385895,
      "open": 1.3523,
      "high": 1.3523,
      "low": 1.3523,
      "close": 1.3523
    },
    {
      "timestamp": 1778673653192,
      "open": 1.3523,
      "high": 1.3523,
      "low": 1.3523,
      "close": 1.3523
    },
    {
      "timestamp": 1778673986127,
      "open": 1.3523,
      "high": 1.3523,
      "low": 1.3523,
      "close": 1.3523
    },
    {
      "timestamp": 1778674232009,
      "open": 1.3523,
      "high": 1.3523,
      "low": 1.3523,
      "close": 1.3523
    },
    {
      "timestamp": 1778674579919,
      "open": 1.3523,
      "high": 1.3523,
      "low": 1.3523,
      "close": 1.3523
    },
    {
      "timestamp": 1778674827736,
      "open": 1.3523,
      "high": 1.3523,
      "low": 1.3523,
      "close": 1.3523
    },
    {
      "timestamp": 1778675186046,
      "open": 1.3523,
      "high": 1.3523,
      "low": 1.3523,
      "close": 1.3523
    },
    {
      "timestamp": 1778675445287,
      "open": 1.3523,
      "high": 1.3523,
      "low": 1.3523,
      "close": 1.3523
    },
    {
      "timestamp": 1778675786272,
      "open": 1.3523,
      "high": 1.3523,
      "low": 1.3523,
      "close": 1.3523
    },
    {
      "timestamp": 1778676027834,
      "open": 1.3523,
      "high": 1.3523,
      "low": 1.3523,
      "close": 1.3523
    },
    {
      "timestamp": 1778676381716,
      "open": 1.3523,
      "high": 1.3523,
      "low": 1.3523,
      "close": 1.3523
    },
    {
      "timestamp": 1778676631462,
      "open": 1.3523,
      "high": 1.3523,
      "low": 1.3523,
      "close": 1.3523
    },
    {
      "timestamp": 1778676980432,
      "open": 1.3523,
      "high": 1.3523,
      "low": 1.3523,
      "close": 1.3523
    },
    {
      "timestamp": 1778677259653,
      "open": 1.3523,
      "high": 1.3523,
      "low": 1.3523,
      "close": 1.3523
    },
    {
      "timestamp": 1778677580133,
      "open": 1.3523,
      "high": 1.3523,
      "low": 1.3523,
      "close": 1.3523
    },
    {
      "timestamp": 1778677829194,
      "open": 1.3523,
      "high": 1.3523,
      "low": 1.3523,
      "close": 1.3523
    },
    {
      "timestamp": 1778678187681,
      "open": 1.3523,
      "high": 1.3523,
      "low": 1.3523,
      "close": 1.3523
    },
    {
      "timestamp": 1778678545057,
      "open": 1.3523,
      "high": 1.3523,
      "low": 1.3523,
      "close": 1.3523
    },
    {
      "timestamp": 1778678784477,
      "open": 1.3523,
      "high": 1.3523,
      "low": 1.3523,
      "close": 1.3523
    },
    {
      "timestamp": 1778679041540,
      "open": 1.3523,
      "high": 1.3523,
      "low": 1.3523,
      "close": 1.3523
    },
    {
      "timestamp": 1778679391028,
      "open": 1.3523,
      "high": 1.3523,
      "low": 1.3523,
      "close": 1.3523
    },
    {
      "timestamp": 1778679628687,
      "open": 1.3523,
      "high": 1.3523,
      "low": 1.3523,
      "close": 1.3523
    },
    {
      "timestamp": 1778679983508,
      "open": 1.3523,
      "high": 1.3523,
      "low": 1.3523,
      "close": 1.3523
    },
    {
      "timestamp": 1778680257783,
      "open": 1.3523,
      "high": 1.3523,
      "low": 1.3523,
      "close": 1.3523
    },
    {
      "timestamp": 1778680588063,
      "open": 1.3523,
      "high": 1.3523,
      "low": 1.3523,
      "close": 1.3523
    },
    {
      "timestamp": 1778680942702,
      "open": 1.3523,
      "high": 1.3523,
      "low": 1.3523,
      "close": 1.3523
    },
    {
      "timestamp": 1778681302534,
      "open": 1.3523,
      "high": 1.3523,
      "low": 1.3523,
      "close": 1.3523
    },
    {
      "timestamp": 1778681428852,
      "open": 1.3523,
      "high": 1.3523,
      "low": 1.3523,
      "close": 1.3523
    },
    {
      "timestamp": 1778681793081,
      "open": 1.3523,
      "high": 1.3523,
      "low": 1.3523,
      "close": 1.3523
    },
    {
      "timestamp": 1778682030531,
      "open": 1.3523,
      "high": 1.3523,
      "low": 1.3523,
      "close": 1.3523
    },
    {
      "timestamp": 1778682385197,
      "open": 1.3523,
      "high": 1.3523,
      "low": 1.3523,
      "close": 1.3523
    },
    {
      "timestamp": 1778682644663,
      "open": 1.351,
      "high": 1.351,
      "low": 1.351,
      "close": 1.351
    },
    {
      "timestamp": 1778682985477,
      "open": 1.351,
      "high": 1.351,
      "low": 1.351,
      "close": 1.351
    },
    {
      "timestamp": 1778683232904,
      "open": 1.351,
      "high": 1.351,
      "low": 1.351,
      "close": 1.351
    },
    {
      "timestamp": 1778683590784,
      "open": 1.351,
      "high": 1.351,
      "low": 1.351,
      "close": 1.351
    },
    {
      "timestamp": 1778683830263,
      "open": 1.351,
      "high": 1.351,
      "low": 1.351,
      "close": 1.351
    },
    {
      "timestamp": 1778684186463,
      "open": 1.351,
      "high": 1.351,
      "low": 1.351,
      "close": 1.351
    },
    {
      "timestamp": 1778684458733,
      "open": 1.351,
      "high": 1.351,
      "low": 1.351,
      "close": 1.351
    },
    {
      "timestamp": 1778684782976,
      "open": 1.351,
      "high": 1.351,
      "low": 1.351,
      "close": 1.351
    },
    {
      "timestamp": 1778685030717,
      "open": 1.351,
      "high": 1.351,
      "low": 1.351,
      "close": 1.351
    },
    {
      "timestamp": 1778685391533,
      "open": 1.351,
      "high": 1.351,
      "low": 1.351,
      "close": 1.351
    },
    {
      "timestamp": 1778685631803,
      "open": 1.351,
      "high": 1.351,
      "low": 1.351,
      "close": 1.351
    },
    {
      "timestamp": 1778685980676,
      "open": 1.351,
      "high": 1.351,
      "low": 1.351,
      "close": 1.351
    },
    {
      "timestamp": 1778686256929,
      "open": 1.351,
      "high": 1.351,
      "low": 1.351,
      "close": 1.351
    },
    {
      "timestamp": 1778686587337,
      "open": 1.351,
      "high": 1.351,
      "low": 1.351,
      "close": 1.351
    },
    {
      "timestamp": 1778686838994,
      "open": 1.351,
      "high": 1.351,
      "low": 1.351,
      "close": 1.351
    },
    {
      "timestamp": 1778687185657,
      "open": 1.351,
      "high": 1.351,
      "low": 1.351,
      "close": 1.351
    },
    {
      "timestamp": 1778687430741,
      "open": 1.351,
      "high": 1.351,
      "low": 1.351,
      "close": 1.351
    },
    {
      "timestamp": 1778687786724,
      "open": 1.351,
      "high": 1.351,
      "low": 1.351,
      "close": 1.351
    },
    {
      "timestamp": 1778688060470,
      "open": 1.351,
      "high": 1.351,
      "low": 1.351,
      "close": 1.351
    },
    {
      "timestamp": 1778688385792,
      "open": 1.351,
      "high": 1.351,
      "low": 1.351,
      "close": 1.351
    },
    {
      "timestamp": 1778688635346,
      "open": 1.351,
      "high": 1.351,
      "low": 1.351,
      "close": 1.351
    },
    {
      "timestamp": 1778688993143,
      "open": 1.351,
      "high": 1.351,
      "low": 1.351,
      "close": 1.351
    },
    {
      "timestamp": 1778689249897,
      "open": 1.351,
      "high": 1.351,
      "low": 1.351,
      "close": 1.351
    },
    {
      "timestamp": 1778689593048,
      "open": 1.351,
      "high": 1.351,
      "low": 1.351,
      "close": 1.351
    },
    {
      "timestamp": 1778689854138,
      "open": 1.351,
      "high": 1.351,
      "low": 1.351,
      "close": 1.351
    },
    {
      "timestamp": 1778690186494,
      "open": 1.351,
      "high": 1.351,
      "low": 1.351,
      "close": 1.351
    },
    {
      "timestamp": 1778690427811,
      "open": 1.351,
      "high": 1.351,
      "low": 1.351,
      "close": 1.351
    },
    {
      "timestamp": 1778690781057,
      "open": 1.351,
      "high": 1.351,
      "low": 1.351,
      "close": 1.351
    },
    {
      "timestamp": 1778691044760,
      "open": 1.351,
      "high": 1.351,
      "low": 1.351,
      "close": 1.351
    },
    {
      "timestamp": 1778691379692,
      "open": 1.351,
      "high": 1.351,
      "low": 1.351,
      "close": 1.351
    },
    {
      "timestamp": 1778691665632,
      "open": 1.351,
      "high": 1.351,
      "low": 1.351,
      "close": 1.351
    },
    {
      "timestamp": 1778691985760,
      "open": 1.351,
      "high": 1.351,
      "low": 1.351,
      "close": 1.351
    },
    {
      "timestamp": 1778692237495,
      "open": 1.351,
      "high": 1.351,
      "low": 1.351,
      "close": 1.351
    },
    {
      "timestamp": 1778692588479,
      "open": 1.351,
      "high": 1.351,
      "low": 1.351,
      "close": 1.351
    },
    {
      "timestamp": 1778692834912,
      "open": 1.351,
      "high": 1.351,
      "low": 1.351,
      "close": 1.351
    },
    {
      "timestamp": 1778693193305,
      "open": 1.351,
      "high": 1.351,
      "low": 1.351,
      "close": 1.351
    },
    {
      "timestamp": 1778693450119,
      "open": 1.351,
      "high": 1.351,
      "low": 1.351,
      "close": 1.351
    },
    {
      "timestamp": 1778693795777,
      "open": 1.351,
      "high": 1.351,
      "low": 1.351,
      "close": 1.351
    },
    {
      "timestamp": 1778694038562,
      "open": 1.351,
      "high": 1.351,
      "low": 1.351,
      "close": 1.351
    },
    {
      "timestamp": 1778694406075,
      "open": 1.351,
      "high": 1.351,
      "low": 1.351,
      "close": 1.351
    },
    {
      "timestamp": 1778694656050,
      "open": 1.351,
      "high": 1.351,
      "low": 1.351,
      "close": 1.351
    },
    {
      "timestamp": 1778694988305,
      "open": 1.351,
      "high": 1.351,
      "low": 1.351,
      "close": 1.351
    },
    {
      "timestamp": 1778695257119,
      "open": 1.351,
      "high": 1.351,
      "low": 1.351,
      "close": 1.351
    },
    {
      "timestamp": 1778695580802,
      "open": 1.351,
      "high": 1.351,
      "low": 1.351,
      "close": 1.351
    },
    {
      "timestamp": 1778695829609,
      "open": 1.351,
      "high": 1.351,
      "low": 1.351,
      "close": 1.351
    },
    {
      "timestamp": 1778696188755,
      "open": 1.351,
      "high": 1.351,
      "low": 1.351,
      "close": 1.351
    },
    {
      "timestamp": 1778696429343,
      "open": 1.351,
      "high": 1.351,
      "low": 1.351,
      "close": 1.351
    },
    {
      "timestamp": 1778696787531,
      "open": 1.351,
      "high": 1.351,
      "low": 1.351,
      "close": 1.351
    },
    {
      "timestamp": 1778697047811,
      "open": 1.351,
      "high": 1.351,
      "low": 1.351,
      "close": 1.351
    },
    {
      "timestamp": 1778697380686,
      "open": 1.351,
      "high": 1.351,
      "low": 1.351,
      "close": 1.351
    },
    {
      "timestamp": 1778697638221,
      "open": 1.351,
      "high": 1.351,
      "low": 1.351,
      "close": 1.351
    },
    {
      "timestamp": 1778697988125,
      "open": 1.351,
      "high": 1.351,
      "low": 1.351,
      "close": 1.351
    },
    {
      "timestamp": 1778698231398,
      "open": 1.351,
      "high": 1.351,
      "low": 1.351,
      "close": 1.351
    },
    {
      "timestamp": 1778698585663,
      "open": 1.351,
      "high": 1.351,
      "low": 1.351,
      "close": 1.351
    },
    {
      "timestamp": 1778698861291,
      "open": 1.351,
      "high": 1.351,
      "low": 1.351,
      "close": 1.351
    },
    {
      "timestamp": 1778699182897,
      "open": 1.351,
      "high": 1.351,
      "low": 1.351,
      "close": 1.351
    },
    {
      "timestamp": 1778699437430,
      "open": 1.351,
      "high": 1.351,
      "low": 1.351,
      "close": 1.351
    },
    {
      "timestamp": 1778699779380,
      "open": 1.351,
      "high": 1.351,
      "low": 1.351,
      "close": 1.351
    },
    {
      "timestamp": 1778700032411,
      "open": 1.351,
      "high": 1.351,
      "low": 1.351,
      "close": 1.351
    },
    {
      "timestamp": 1778700385645,
      "open": 1.351,
      "high": 1.351,
      "low": 1.351,
      "close": 1.351
    },
    {
      "timestamp": 1778700642154,
      "open": 1.351,
      "high": 1.351,
      "low": 1.351,
      "close": 1.351
    },
    {
      "timestamp": 1778700989611,
      "open": 1.351,
      "high": 1.351,
      "low": 1.351,
      "close": 1.351
    },
    {
      "timestamp": 1778701227855,
      "open": 1.351,
      "high": 1.351,
      "low": 1.351,
      "close": 1.351
    },
    {
      "timestamp": 1778701584911,
      "open": 1.351,
      "high": 1.351,
      "low": 1.351,
      "close": 1.351
    },
    {
      "timestamp": 1778701828590,
      "open": 1.351,
      "high": 1.351,
      "low": 1.351,
      "close": 1.351
    },
    {
      "timestamp": 1778702186345,
      "open": 1.351,
      "high": 1.351,
      "low": 1.351,
      "close": 1.351
    },
    {
      "timestamp": 1778702452328,
      "open": 1.351,
      "high": 1.351,
      "low": 1.351,
      "close": 1.351
    },
    {
      "timestamp": 1778702780642,
      "open": 1.351,
      "high": 1.351,
      "low": 1.351,
      "close": 1.351
    },
    {
      "timestamp": 1778703039687,
      "open": 1.351,
      "high": 1.351,
      "low": 1.351,
      "close": 1.351
    },
    {
      "timestamp": 1778703392011,
      "open": 1.351,
      "high": 1.351,
      "low": 1.351,
      "close": 1.351
    },
    {
      "timestamp": 1778703636470,
      "open": 1.351,
      "high": 1.351,
      "low": 1.351,
      "close": 1.351
    },
    {
      "timestamp": 1778703980170,
      "open": 1.351,
      "high": 1.351,
      "low": 1.351,
      "close": 1.351
    },
    {
      "timestamp": 1778704241898,
      "open": 1.351,
      "high": 1.351,
      "low": 1.351,
      "close": 1.351
    },
    {
      "timestamp": 1778704582299,
      "open": 1.351,
      "high": 1.351,
      "low": 1.351,
      "close": 1.351
    },
    {
      "timestamp": 1778704829220,
      "open": 1.351,
      "high": 1.351,
      "low": 1.351,
      "close": 1.351
    },
    {
      "timestamp": 1778705185634,
      "open": 1.351,
      "high": 1.351,
      "low": 1.351,
      "close": 1.351
    },
    {
      "timestamp": 1778705431099,
      "open": 1.351,
      "high": 1.351,
      "low": 1.351,
      "close": 1.351
    },
    {
      "timestamp": 1778705786844,
      "open": 1.351,
      "high": 1.351,
      "low": 1.351,
      "close": 1.351
    },
    {
      "timestamp": 1778706056217,
      "open": 1.351,
      "high": 1.351,
      "low": 1.351,
      "close": 1.351
    },
    {
      "timestamp": 1778706380218,
      "open": 1.351,
      "high": 1.351,
      "low": 1.351,
      "close": 1.351
    },
    {
      "timestamp": 1778706633493,
      "open": 1.351,
      "high": 1.351,
      "low": 1.351,
      "close": 1.351
    },
    {
      "timestamp": 1778706987328,
      "open": 1.351,
      "high": 1.351,
      "low": 1.351,
      "close": 1.351
    },
    {
      "timestamp": 1778707236338,
      "open": 1.351,
      "high": 1.351,
      "low": 1.351,
      "close": 1.351
    },
    {
      "timestamp": 1778707585014,
      "open": 1.351,
      "high": 1.351,
      "low": 1.351,
      "close": 1.351
    },
    {
      "timestamp": 1778707845730,
      "open": 1.351,
      "high": 1.351,
      "low": 1.351,
      "close": 1.351
    },
    {
      "timestamp": 1778708186103,
      "open": 1.351,
      "high": 1.351,
      "low": 1.351,
      "close": 1.351
    },
    {
      "timestamp": 1778708430616,
      "open": 1.351,
      "high": 1.351,
      "low": 1.351,
      "close": 1.351
    },
    {
      "timestamp": 1778708780321,
      "open": 1.351,
      "high": 1.351,
      "low": 1.351,
      "close": 1.351
    },
    {
      "timestamp": 1778709029444,
      "open": 1.351,
      "high": 1.351,
      "low": 1.351,
      "close": 1.351
    },
    {
      "timestamp": 1778709380233,
      "open": 1.351,
      "high": 1.351,
      "low": 1.351,
      "close": 1.351
    },
    {
      "timestamp": 1778709660998,
      "open": 1.351,
      "high": 1.351,
      "low": 1.351,
      "close": 1.351
    },
    {
      "timestamp": 1778709988107,
      "open": 1.351,
      "high": 1.351,
      "low": 1.351,
      "close": 1.351
    },
    {
      "timestamp": 1778710236226,
      "open": 1.351,
      "high": 1.351,
      "low": 1.351,
      "close": 1.351
    },
    {
      "timestamp": 1778710586778,
      "open": 1.351,
      "high": 1.351,
      "low": 1.351,
      "close": 1.351
    },
    {
      "timestamp": 1778710836458,
      "open": 1.351,
      "high": 1.351,
      "low": 1.351,
      "close": 1.351
    },
    {
      "timestamp": 1778711185408,
      "open": 1.351,
      "high": 1.351,
      "low": 1.351,
      "close": 1.351
    },
    {
      "timestamp": 1778711451830,
      "open": 1.351,
      "high": 1.351,
      "low": 1.351,
      "close": 1.351
    },
    {
      "timestamp": 1778711784932,
      "open": 1.351,
      "high": 1.351,
      "low": 1.351,
      "close": 1.351
    },
    {
      "timestamp": 1778712035810,
      "open": 1.351,
      "high": 1.351,
      "low": 1.351,
      "close": 1.351
    },
    {
      "timestamp": 1778712387945,
      "open": 1.351,
      "high": 1.351,
      "low": 1.351,
      "close": 1.351
    },
    {
      "timestamp": 1778712628824,
      "open": 1.351,
      "high": 1.351,
      "low": 1.351,
      "close": 1.351
    },
    {
      "timestamp": 1778712979964,
      "open": 1.351,
      "high": 1.351,
      "low": 1.351,
      "close": 1.351
    },
    {
      "timestamp": 1778713259067,
      "open": 1.351,
      "high": 1.351,
      "low": 1.351,
      "close": 1.351
    },
    {
      "timestamp": 1778713585570,
      "open": 1.351,
      "high": 1.351,
      "low": 1.351,
      "close": 1.351
    },
    {
      "timestamp": 1778713828178,
      "open": 1.351,
      "high": 1.351,
      "low": 1.351,
      "close": 1.351
    },
    {
      "timestamp": 1778714180268,
      "open": 1.351,
      "high": 1.351,
      "low": 1.351,
      "close": 1.351
    },
    {
      "timestamp": 1778714427121,
      "open": 1.351,
      "high": 1.351,
      "low": 1.351,
      "close": 1.351
    },
    {
      "timestamp": 1778714788533,
      "open": 1.351,
      "high": 1.351,
      "low": 1.351,
      "close": 1.351
    },
    {
      "timestamp": 1778715041563,
      "open": 1.351,
      "high": 1.351,
      "low": 1.351,
      "close": 1.351
    },
    {
      "timestamp": 1778715387457,
      "open": 1.351,
      "high": 1.351,
      "low": 1.351,
      "close": 1.351
    },
    {
      "timestamp": 1778715633693,
      "open": 1.351,
      "high": 1.351,
      "low": 1.351,
      "close": 1.351
    },
    {
      "timestamp": 1778715995808,
      "open": 1.351,
      "high": 1.351,
      "low": 1.351,
      "close": 1.351
    },
    {
      "timestamp": 1778716236986,
      "open": 1.351,
      "high": 1.351,
      "low": 1.351,
      "close": 1.351
    },
    {
      "timestamp": 1778716583882,
      "open": 1.351,
      "high": 1.351,
      "low": 1.351,
      "close": 1.351
    },
    {
      "timestamp": 1778716863016,
      "open": 1.351,
      "high": 1.351,
      "low": 1.351,
      "close": 1.351
    },
    {
      "timestamp": 1778717180431,
      "open": 1.351,
      "high": 1.351,
      "low": 1.351,
      "close": 1.351
    },
    {
      "timestamp": 1778717435348,
      "open": 1.351,
      "high": 1.351,
      "low": 1.351,
      "close": 1.351
    }
  ],
  "currentPrice": 1.351,
  "timestamp": 1778717785371,
  "high": 1.3523,
  "low": 1.351,
  "change": 0
}